swap/__init__.py
swap/exceptions.py
swap/utils.py
swap/cli/__init__.py
swap/cli/__main__.py
swap/cli/providers/__init__.py
swap/cli/providers/bitcoin/__init__.py
swap/cli/providers/bitcoin/decode.py
swap/cli/providers/bitcoin/fund.py
swap/cli/providers/bitcoin/htlc.py
swap/cli/providers/bitcoin/refund.py
swap/cli/providers/bitcoin/signature.py
swap/cli/providers/bitcoin/submit.py
swap/cli/providers/bitcoin/withdraw.py
swap/cli/providers/bytom/__init__.py
swap/cli/providers/bytom/decode.py
swap/cli/providers/bytom/fund.py
swap/cli/providers/bytom/htlc.py
swap/cli/providers/bytom/refund.py
swap/cli/providers/bytom/signature.py
swap/cli/providers/bytom/submit.py
swap/cli/providers/bytom/withdraw.py
swap/cli/providers/ethereum/__init__.py
swap/cli/providers/ethereum/decode.py
swap/cli/providers/ethereum/fund.py
swap/cli/providers/ethereum/htlc.py
swap/cli/providers/ethereum/refund.py
swap/cli/providers/ethereum/signature.py
swap/cli/providers/ethereum/submit.py
swap/cli/providers/ethereum/withdraw.py
swap/cli/providers/vapor/__init__.py
swap/cli/providers/vapor/decode.py
swap/cli/providers/vapor/fund.py
swap/cli/providers/vapor/htlc.py
swap/cli/providers/vapor/refund.py
swap/cli/providers/vapor/signature.py
swap/cli/providers/vapor/submit.py
swap/cli/providers/vapor/withdraw.py
swap/cli/providers/xinfin/__init__.py
swap/cli/providers/xinfin/decode.py
swap/cli/providers/xinfin/fund.py
swap/cli/providers/xinfin/htlc.py
swap/cli/providers/xinfin/refund.py
swap/cli/providers/xinfin/signature.py
swap/cli/providers/xinfin/submit.py
swap/cli/providers/xinfin/withdraw.py
swap/providers/__init__.py
swap/providers/config.py
swap/providers/bitcoin/__init__.py
swap/providers/bitcoin/htlc.py
swap/providers/bitcoin/rpc.py
swap/providers/bitcoin/signature.py
swap/providers/bitcoin/solver.py
swap/providers/bitcoin/transaction.py
swap/providers/bitcoin/utils.py
swap/providers/bitcoin/wallet.py
swap/providers/bitcoin/contracts/htlc.script
swap/providers/bytom/__init__.py
swap-0.5.0.dist-info/LICENSE
swap-0.5.0.dist-info/METADATA
swap-0.5.0.dist-info/WHEEL
swap-0.5.0.dist-info/entry_points.txt
swap-0.5.0.dist-info/top_level.txt
swap-0.5.0.dist-info/RECORD
