Metadata-Version: 2.1
Name: swap
Version: 0.5.0
Summary: Cross-chain atomic swap between the networks of two cryptocurrencies based on Hash Time Lock Contracts (HTLC's) protocol.
Home-page: https://github.com/movnetwork/swap
Author: Meheret Tesfaye Batu
Author-email: meherett@zoho.com
License: AGPL-3.0
Keywords: cross-chain,atomic-swap,swap,htlc,bitcoin,bytom,ethereum,vapor,xinfin,cryptocurrencies
Platform: UNKNOWN
Classifier: Development Status :: 3 - Alpha
Classifier: License :: OSI Approved :: GNU Affero General Public License v3
Classifier: Programming Language :: Python :: 3.6
Classifier: Programming Language :: Python :: 3.7
Classifier: Programming Language :: Python :: 3.8
Classifier: Programming Language :: Python :: 3.9
Classifier: Topic :: Software Development
Requires-Python: >=3.6,<4
Provides-Extra: tests
Provides-Extra: docs
License-File: LICENSE
